LICENSE
MANIFEST.in
README.rst
setup.py
geokey_geotagx/__init__.py
geokey_geotagx/urls.py
geokey_geotagx/views.py
geokey_geotagx.egg-info/PKG-INFO
geokey_geotagx.egg-info/SOURCES.txt
geokey_geotagx.egg-info/dependency_links.txt
geokey_geotagx.egg-info/top_level.txt