Metadata-Version: 1.1
Name: geokey-geotagx
Version: 0.2.0
Summary: Import results from GeoTag-X
Home-page: https://github.com/ExCiteS/geokey-geotagx
Author: ExCiteS
Author-email: excites@ucl.ac.uk
License: MIT
Download-URL: https://github.com/ExCiteS/geokey-geotagx/tarball/0.2.0
Platform: UNKNOWN
